multiarmedbandits/__init__.py
multiarmedbandits-0.1.0.dist-info/LICENSE
multiarmedbandits-0.1.0.dist-info/METADATA
multiarmedbandits-0.1.0.dist-info/WHEEL
multiarmedbandits-0.1.0.dist-info/top_level.txt
multiarmedbandits-0.1.0.dist-info/RECORD
